SpotGraph/__init__.py
SpotGraph/formats.py
SpotGraph/graphs.py
SpotGraph/simple_metrics.py
SpotGraph-0.0.1.dist-info/LICENSE
SpotGraph-0.0.1.dist-info/METADATA
SpotGraph-0.0.1.dist-info/WHEEL
SpotGraph-0.0.1.dist-info/top_level.txt
SpotGraph-0.0.1.dist-info/RECORD
